goodman_photometry/__init__.py
goodman_photometry/astrometry.py
goodman_photometry/goodman_astro.py
goodman_photometry/photometry.py
goodman_photometry/utils.py
goodman_photometry/version.py
goodman_photometry/tests/__init__.py
goodman_photometry/tests/test_goodman_astro.py
goodman_photometry-1.1.0.dist-info/METADATA
goodman_photometry-1.1.0.dist-info/WHEEL
goodman_photometry-1.1.0.dist-info/entry_points.txt
goodman_photometry-1.1.0.dist-info/top_level.txt
goodman_photometry-1.1.0.dist-info/RECORD
