Metadata-Version: 2.4
Name: goodman_photometry
Version: 1.1.0
Summary: Pipeline for reducing Goodman HTS data.
Author-email: Felipe Navarete <felipe.navarete@noirlab.edu>
Maintainer-email: Felipe Navarete <felipe.navarete@noirlab.edu>, Simón Torres <simon.torres@noirlab.edu>
Project-URL: Homepage, https://github.com/soar-telescope/goodman_photometry
Project-URL: Bug Reports, https://github.com/soar-telescope/goodman_photometry/issues
Project-URL: Source, https://github.com/soar-telescope/goodman_photometry
Keywords: soar,pipelines,astronomy,images,astrometry,photometry
Classifier: Development Status :: 5 - Production/Stable
Classifier: Environment :: Console
Classifier: Intended Audience :: Developers
Classifier: Intended Audience :: Education
Classifier: Intended Audience :: Science/Research
Classifier: License :: OSI Approved :: BSD License
Classifier: Programming Language :: Python :: 3.8
Classifier: Programming Language :: Python :: 3.9
Classifier: Programming Language :: Python :: 3.10
Classifier: Programming Language :: Python :: 3.11
Classifier: Programming Language :: Python :: 3.12
Classifier: Natural Language :: English
Classifier: Operating System :: POSIX :: Linux
Classifier: Operating System :: POSIX :: Other
Classifier: Operating System :: MacOS :: MacOS X
Classifier: Topic :: Scientific/Engineering :: Astronomy
Classifier: Topic :: Scientific/Engineering :: Information Analysis
Classifier: Topic :: Software Development :: Libraries :: Python Modules
Requires-Python: >=3.10
Requires-Dist: astropy
Requires-Dist: astroplan
Requires-Dist: ccdproc
Requires-Dist: cython
Requires-Dist: matplotlib
Requires-Dist: numpy
Requires-Dist: packaging
Requires-Dist: pandas
Requires-Dist: requests
Requires-Dist: scipy
Requires-Dist: statsmodels
Requires-Dist: astroquery
Requires-Dist: sip_tpv
Requires-Dist: setuptools
